Workbook
Name IQ_CH: 110000
Name IQ_CQ: 5000
Name IQ_CY: 10000
Name IQ_DAILY: 500000
Name IQ_FH: 100000
Name IQ_FQ: 500
Name IQ_FY: 1000
Name IQ_LTM: 2000
Name IQ_MONTH: 15000
Name IQ_NTM: 6000
Name IQ_WEEK: 50000
Name IQ_YTD: 3000
Name UPDATE: 'Data Sheet'!$E$1

Sheet Financials>

Sheet Financial Statements
B2: YEARS | D2: ="Financials"&" - "&'Data Sheet'!B1 -> Financials - MAHINDRA & MAHINDRA LTD
D3: =IFERROR('Data Sheet'!B16,0) -> 42460 | E3: =IFERROR('Data Sheet'!C16,0) -> 42825 | F3: =IFERROR('Data Sheet'!D16,0) -> 43190 | G3: =IFERROR('Data Sheet'!E16,0) -> 43555 | H3: =IFERROR('Data Sheet'!F16,0) -> 43921 | I3: =IFERROR('Data Sheet'!G16,0) -> 44286 | J3: =IFERROR('Data Sheet'!H16,0) -> 44651 | K3: =IFERROR('Data Sheet'!I16,0) -> 45016 | ... M3: =IFERROR('Data Sheet'!K16,0) -> 45747 | N3: LTM
A5: # | B5: Proft & Loss Statement
B6: In Crores
B7: Sales | D7: =IFERROR('Data Sheet'!B17,0) -> 75841.42 | E7: =IFERROR('Data Sheet'!C17,0) -> 83773.05 | F7: =IFERROR('Data Sheet'!D17,0) -> 92093.95 | G7: =IFERROR('Data Sheet'!E17,0) -> 104720.68 | H7: =IFERROR('Data Sheet'!F17,0) -> 75381.93 | I7: =IFERROR('Data Sheet'!G17,0) -> 74277.78 | J7: =IFERROR('Data Sheet'!H17,0) -> 90170.57 | K7: =IFERROR('Data Sheet'!I17,0) -> 121268.55 | ... M7: =IFERROR('Data Sheet'!K17,0) -> 159210.82 | N7: =IFERROR(SUM('Data Sheet'!H42:K42),0) -> 175704.22
B8: Sales Growth | E8: =E7/D7-1 -> 0.10458177 | F8: =F7/E7-1 -> 0.099326693 | G8: =G7/F7-1 -> 0.13710705 | H8: =H7/G7-1 -> -0.28016195 | I8: =I7/H7-1 -> -0.01464741 | J8: =J7/I7-1 -> 0.21396426 | K8: =K7/J7-1 -> 0.34487949 | L8: =L7/K7-1 -> 0.14686182 | ... N8: =N7/M7-1 -> 0.10359472
B10: Cost of goods sold | D10: =IFERROR(SUM('Data Sheet'!B18,'Data Sheet'!B20:B22)-1*'Data Sheet'!B19,0) -> 56073.91 | E10: =IFERROR(SUM('Data Sheet'!C18,'Data Sheet'!C20:C22)-1*'Data Sheet'!C19,0) -> 63464.36 | F10: =IFERROR(SUM('Data Sheet'!D18,'Data Sheet'!D20:D22)-1*'Data Sheet'!D19,0) -> 67869.4 | G10: =IFERROR(SUM('Data Sheet'!E18,'Data Sheet'!E20:E22)-1*'Data Sheet'!E19,0) -> 76462.9 | H10: =IFERROR(SUM('Data Sheet'!F18,'Data Sheet'!F20:F22)-1*'Data Sheet'!F19,0) -> 50445.45 | I10: =IFERROR(SUM('Data Sheet'!G18,'Data Sheet'!G20:G22)-1*'Data Sheet'!G19,0) -> 49173.01 | J10: =IFERROR(SUM('Data Sheet'!H18,'Data Sheet'!H20:H22)-1*'Data Sheet'!H19,0) -> 63855.47 | K10: =IFERROR(SUM('Data Sheet'!I18,'Data Sheet'!I20:I22)-1*'Data Sheet'!I19,0) -> 88334.41 | ... M10: =IFERROR(SUM('Data Sheet'!K18,'Data Sheet'!K20:K22)-1*'Data Sheet'!K19,0) -> 111863.52 | N10: =IFERROR(SUM('Data Sheet'!H43:K43),0) -> 142405.66
B11: % Sales | D11: =D10/D7 -> 0.73935733 | E11: =E10/E7 -> 0.7575749 | F11: =F10/F7 -> 0.73695829 | G11: =G10/G7 -> 0.73016046 | H11: =H10/H7 -> 0.66919818 | I11: =I10/I7 -> 0.66201507 | J11: =J10/J7 -> 0.7081631 | K11: =K10/K7 -> 0.72841978 | ... N11: =N10/N7 -> 0.81048514
B13: Gross profit | D13: =IFERROR((D7-D10),0) -> 19767.51 | E13: =IFERROR((E7-E10),0) -> 20308.69 | F13: =IFERROR((F7-F10),0) -> 24224.55 | G13: =IFERROR((G7-G10),0) -> 28257.78 | H13: =IFERROR((H7-H10),0) -> 24936.48 | I13: =IFERROR((I7-I10),0) -> 25104.77 | J13: =IFERROR((J7-J10),0) -> 26315.1 | K13: =IFERROR((K7-K10),0) -> 32934.14 | ... N13: =IFERROR((N7-N10),0) -> 33298.56
B14: % Sales | D14: =D13/D7 -> 0.26064267 | E14: =E13/E7 -> 0.2424251 | F14: =F13/F7 -> 0.26304171 | G14: =G13/G7 -> 0.26983954 | H14: =H13/H7 -> 0.33080182 | I14: =I13/I7 -> 0.33798493 | J14: =J13/J7 -> 0.2918369 | K14: =K13/K7 -> 0.27158022 | ... N14: =N13/N7 -> 0.18951486
B16: Selling & General Expenses | D16: =IFERROR(SUM('Data Sheet'!B23:B24),0) -> 9685.07 | E16: =IFERROR(SUM('Data Sheet'!C23:C24),0) -> 9573.86 | F16: =IFERROR(SUM('Data Sheet'!D23:D24),0) -> 10998.45 | G16: =IFERROR(SUM('Data Sheet'!E23:E24),0) -> 13051.27 | H16: =IFERROR(SUM('Data Sheet'!F23:F24),0) -> 14778.73 | I16: =IFERROR(SUM('Data Sheet'!G23:G24),0) -> 13617.75 | J16: =IFERROR(SUM('Data Sheet'!H23:H24),0) -> 11632.25 | K16: =IFERROR(SUM('Data Sheet'!I23:I24),0) -> 12648.85 | ... N16: =IFERROR(SUM('Data Sheet'!L23:L24),0) -> 0
B17: % Sales | D17: =D16/D7 -> 0.12770159 | E17: =E16/E7 -> 0.11428329 | F17: =F16/F7 -> 0.11942641 | G17: =G16/G7 -> 0.12462935 | H17: =H16/H7 -> 0.19605136 | I17: =I16/I7 -> 0.18333545 | J17: =J16/J7 -> 0.12900273 | K17: =K16/K7 -> 0.10430445 | ... N17: =N16/N7 -> 0
B19: EBITDA | D19: =IFERROR((D13-D16),0) -> 10082.44 | E19: =IFERROR((E13-E16),0) -> 10734.83 | F19: =IFERROR((F13-F16),0) -> 13226.1 | G19: =IFERROR((G13-G16),0) -> 15206.51 | H19: =IFERROR((H13-H16),0) -> 10157.75 | I19: =IFERROR((I13-I16),0) -> 11487.02 | J19: =IFERROR((J13-J16),0) -> 14682.85 | K19: =IFERROR((K13-K16),0) -> 20285.29 | ... N19: =IFERROR((N13-N16),0) -> 33298.56
B20: EBITDA Margins | D20: =D19/D7 -> 0.13294108 | E20: =E19/E7 -> 0.12814181 | F20: =F19/F7 -> 0.1436153 | G20: =G19/G7 -> 0.14521019 | H20: =H19/H7 -> 0.13475046 | I20: =I19/I7 -> 0.15464948 | J20: =J19/J7 -> 0.16283417 | K20: =K19/K7 -> 0.16727577 | ... N20: =N19/N7 -> 0.18951486
B22: Interest | D22: =IFERROR('Data Sheet'!B27,0) -> 3367.59 | E22: =IFERROR('Data Sheet'!C27,0) -> 3648.46 | F22: =IFERROR('Data Sheet'!D27,0) -> 3987.09 | G22: =IFERROR('Data Sheet'!E27,0) -> 5021.35 | H22: =IFERROR('Data Sheet'!F27,0) -> 6021.15 | I22: =IFERROR('Data Sheet'!G27,0) -> 6102.22 | J22: =IFERROR('Data Sheet'!H27,0) -> 5018.05 | K22: =IFERROR('Data Sheet'!I27,0) -> 5829.7 | ... M22: =IFERROR('Data Sheet'!K27,0) -> 9083.39 | N22: =IFERROR(SUM('Data Sheet'!H46:K46),0) -> 9536.9
B23: % Sales | D23: =D22/D7 -> 0.044403045 | E23: =E22/E7 -> 0.043551715 | F23: =F22/F7 -> 0.043293723 | G23: =G22/G7 -> 0.047949937 | H23: =H22/H7 -> 0.079875243 | I23: =I22/I7 -> 0.082154044 | J23: =J22/J7 -> 0.055650641 | K23: =K22/K7 -> 0.048072645 | ... N23: =N22/N7 -> 0.05427815
B25: Depreciation | D25: =IFERROR('Data Sheet'!B26,0) -> 2441.65 | E25: =IFERROR('Data Sheet'!C26,0) -> 2812.72 | F25: =IFERROR('Data Sheet'!D26,0) -> 3279.9 | G25: =IFERROR('Data Sheet'!E26,0) -> 3990.77 | H25: =IFERROR('Data Sheet'!F26,0) -> 3366.68 | I25: =IFERROR('Data Sheet'!G26,0) -> 3378.11 | J25: =IFERROR('Data Sheet'!H26,0) -> 3507.5 | K25: =IFERROR('Data Sheet'!I26,0) -> 4356.81 | ... M25: =IFERROR('Data Sheet'!K26,0) -> 6073.65 | N25: =IFERROR(SUM('Data Sheet'!H45:K45),0) -> 6740.34
B26: % Sales | D26: =D25/D7 -> 0.032194149 | E26: =E25/E7 -> 0.033575476 | F26: =F25/F7 -> 0.035614717 | G26: =G25/G7 -> 0.03810871 | H26: =H25/H7 -> 0.044661632 | I26: =I25/I7 -> 0.045479415 | J26: =J25/J7 -> 0.038898501 | K26: =K25/K7 -> 0.035926957 | ... N26: =N25/N7 -> 0.038361856
B28: Earnings before Tax | D28: =IFERROR((D19-(D22+D25)),0) -> 4273.2 | E28: =IFERROR((E19-(E22+E25)),0) -> 4273.65 | F28: =IFERROR((F19-(F22+F25)),0) -> 5959.11 | G28: =IFERROR((G19-(G22+G25)),0) -> 6194.39 | H28: =IFERROR((H19-(H22+H25)),0) -> 769.92 | I28: =IFERROR((I19-(I22+I25)),0) -> 2006.69 | J28: =IFERROR((J19-(J22+J25)),0) -> 6157.3 | K28: =IFERROR((K19-(K22+K25)),0) -> 10098.78 | ... N28: =IFERROR((N19-(N22+N25)),0) -> 17021.32
B29: % Sales | D29: =D28/D7 -> 0.056343882 | E29: =E28/E7 -> 0.051014616 | F29: =F28/F7 -> 0.064706856 | G29: =G28/G7 -> 0.059151545 | H29: =H28/H7 -> 0.010213588 | I29: =I28/I7 -> 0.02701602 | J29: =J28/J7 -> 0.068285029 | K29: =K28/K7 -> 0.083276167 | ... N29: =N28/N7 -> 0.09687485
B31: Tax | D31: =IFERROR('Data Sheet'!B29,0) -> 2117.53 | E31: =IFERROR('Data Sheet'!C29,0) -> 2299.73 | F31: =IFERROR('Data Sheet'!D29,0) -> 2367.73 | G31: =IFERROR('Data Sheet'!E29,0) -> 2853.99 | H31: =IFERROR('Data Sheet'!F29,0) -> 1975.61 | I31: =IFERROR('Data Sheet'!G29,0) -> 1645.81 | J31: =IFERROR('Data Sheet'!H29,0) -> 2108.76 | K31: =IFERROR('Data Sheet'!I29,0) -> 2685.75 | ... M31: =IFERROR('Data Sheet'!K29,0) -> 5006.45 | N31: =IFERROR(SUM('Data Sheet'!H48:K48),0) -> 5914.17
B32: Effective Tax Rate | D32: =D31/D28 -> 0.4955373 | E32: =E31/E28 -> 0.53811847 | F32: =F31/F28 -> 0.39732947 | G32: =G31/G28 -> 0.46073786 | H32: =H31/H28 -> 2.5659939 | I32: =I31/I28 -> 0.82016156 | J32: =J31/J28 -> 0.34248128 | K32: =K31/K28 -> 0.26594797 | ... N32: =N31/N28 -> 0.3474566
B34: Net profit | D34: =IFERROR((D28-D31),0) -> 2155.67 | E34: =IFERROR((E28-E31),0) -> 1973.92 | F34: =IFERROR((F28-F31),0) -> 3591.38 | G34: =IFERROR((G28-G31),0) -> 3340.4 | H34: =IFERROR((H28-H31),0) -> -1205.69 | I34: =IFERROR((I28-I31),0) -> 360.88 | J34: =IFERROR((J28-J31),0) -> 4048.54 | K34: =IFERROR((K28-K31),0) -> 7413.03 | ... N34: =IFERROR((N28-N31),0) -> 11107.15
B35: Net Margin | D35: =D34/D7 -> 0.028423387 | E35: =E34/E7 -> 0.023562709 | F35: =F34/F7 -> 0.038996916 | G35: =G34/G7 -> 0.031898189 | H35: =H34/H7 -> -0.015994417 | I35: =I34/I7 -> 0.0048585189 | J35: =J34/J7 -> 0.044898685 | K35: =K34/K7 -> 0.06112904 | ... N35: =N34/N7 -> 0.063215044
B37: Number of Equity Shares (in Cr) | D37: =IFERROR('Data Sheet'!B93,0) -> 124.22 | E37: =IFERROR('Data Sheet'!C93,0) -> 124.22 | F37: =IFERROR('Data Sheet'!D93,0) -> 124.32 | G37: =IFERROR('Data Sheet'!E93,0) -> 124.32 | H37: =IFERROR('Data Sheet'!F93,0) -> 124.32 | I37: =IFERROR('Data Sheet'!G93,0) -> 124.32 | J37: =IFERROR('Data Sheet'!H93,0) -> 124.32 | K37: =IFERROR('Data Sheet'!I93,0) -> 124.35 | ... M37: =IFERROR('Data Sheet'!K93,0) -> 124.35 | N37: =M37 -> 124.35
B39: Earnings Per Share | D39: =IFERROR((D34/D37),0) -> 17.353647 | E39: =IFERROR((E34/E37),0) -> 15.890517 | F39: =IFERROR((F34/F37),0) -> 28.888192 | G39: =IFERROR((G34/G37),0) -> 26.869369 | H39: =IFERROR((H34/H37),0) -> -9.6982786 | I39: =IFERROR((I34/I37),0) -> 2.9028314 | J39: =IFERROR((J34/J37),0) -> 32.565476 | K39: =IFERROR((K34/K37),0) -> 59.614234 | ... N39: =IFERROR((N34/N37),0) -> 89.321673
B40: EPS Growth | D40: =0 -> 0 | E40: =E39/D39-1 -> -0.084312534 | F40: =F39/E39-1 -> 0.81795168 | G40: =G39/F39-1 -> -0.069884 | H40: =H39/G39-1 -> -1.3609418 | I40: =I39/H39-1 -> -1.2993141 | J40: =J39/I39-1 -> 10.218521 | K40: =K39/J39-1 -> 0.83059611 | L40: =L39/K39-1 -> 0.21029727 | ... N40: =N39/M39-1 -> 0.072667484
B42: Dividends per share | D42: =IFERROR(('Data Sheet'!B31/'Data Sheet'!B93),0) -> 5.2242795 | E42: =IFERROR(('Data Sheet'!C31/'Data Sheet'!C93),0) -> 6.5 | F42: =IFERROR(('Data Sheet'!D31/'Data Sheet'!D93),0) -> 6.5532497 | G42: =IFERROR(('Data Sheet'!E31/'Data Sheet'!E93),0) -> 7.4383044 | H42: =IFERROR(('Data Sheet'!F31/'Data Sheet'!F93),0) -> 2.0954794 | I42: =IFERROR(('Data Sheet'!G31/'Data Sheet'!G93),0) -> 7.8145914 | J42: =IFERROR(('Data Sheet'!H31/'Data Sheet'!H93),0) -> 10.332207 | K42: =IFERROR(('Data Sheet'!I31/'Data Sheet'!I93),0) -> 14.552955 | ... M42: =IFERROR(('Data Sheet'!K31/'Data Sheet'!K93),0) -> 22.712023 | N42: =M42 -> 22.712023
B43: EPS Growth | D43: =D42/D39 -> 0.30104793 | E43: =E42/E39 -> 0.409049 | F43: =F42/F39 -> 0.22684873 | G43: =G42/G39 -> 0.27683212 | H43: =H42/H39 -> -0.21606715 | I43: =I42/I39 -> 2.6920583 | J43: =J42/J39 -> 0.31727487 | K43: =K42/K39 -> 0.2441188 | ... N43: =N42/N39 -> 0.25427225
B45: Retained Earnings | D45: =IFERROR(IF(D39>D42,1-D43,),0) -> 0.69895207 | E45: =IFERROR(IF(E39>E42,1-E43,),0) -> 0.590951 | F45: =IFERROR(IF(F39>F42,1-F43,),0) -> 0.77315127 | G45: =IFERROR(IF(G39>G42,1-G43,),0) -> 0.72316788 | H45: =IFERROR(IF(H39>H42,1-H43,),0) -> 0 | I45: =IFERROR(IF(I39>I42,1-I43,),0) -> 0 | J45: =IFERROR(IF(J39>J42,1-J43,),0) -> 0.68272513 | K45: =IFERROR(IF(K39>K42,1-K43,),0) -> 0.7558812 | ... N45: =IFERROR(IF(N39>N42,1-N43,),0) -> 0.74572775
A48: # | B48: Balance Sheet
B49: In Crores
B50: Equity Share Capital | D50: =IFERROR('Data Sheet'!B57,0) -> 270.4 | E50: =IFERROR('Data Sheet'!C57,0) -> 310.55 | F50: =IFERROR('Data Sheet'!D57,0) -> 543.13 | G50: =IFERROR('Data Sheet'!E57,0) -> 543.96 | H50: =IFERROR('Data Sheet'!F57,0) -> 554.28 | I50: =IFERROR('Data Sheet'!G57,0) -> 555.15 | J50: =IFERROR('Data Sheet'!H57,0) -> 556.06 | K50: =IFERROR('Data Sheet'!I57,0) -> 556.82 | ... M50: =IFERROR('Data Sheet'!K57,0) -> 558.15
B51: Reserves | D51: =IFERROR('Data Sheet'!B58,0) -> 26222.25 | E51: =IFERROR('Data Sheet'!C58,0) -> 29467.1 | F51: =IFERROR('Data Sheet'!D58,0) -> 36232.06 | G51: =IFERROR('Data Sheet'!E58,0) -> 39439.45 | H51: =IFERROR('Data Sheet'!F58,0) -> 39415.03 | I51: =IFERROR('Data Sheet'!G58,0) -> 41026.77 | J51: =IFERROR('Data Sheet'!H58,0) -> 46566.58 | K51: =IFERROR('Data Sheet'!I58,0) -> 55808.97 | ... M51: =IFERROR('Data Sheet'!K58,0) -> 76480.71
B52: Borrowings | D52: =IFERROR('Data Sheet'!B59,0) -> 41552.93 | E52: =IFERROR('Data Sheet'!C59,0) -> 48761.91 | F52: =IFERROR('Data Sheet'!D59,0) -> 55897.92 | G52: =IFERROR('Data Sheet'!E59,0) -> 70848.3 | H52: =IFERROR('Data Sheet'!F59,0) -> 82092.28 | I52: =IFERROR('Data Sheet'!G59,0) -> 80624.83 | J52: =IFERROR('Data Sheet'!H59,0) -> 77605.21 | K52: =IFERROR('Data Sheet'!I59,0) -> 92246.85 | ... M52: =IFERROR('Data Sheet'!K59,0) -> 129024.58
B53: Other Liabilities | D53: =IFERROR('Data Sheet'!B60,0) -> 31806.24 | E53: =IFERROR('Data Sheet'!C60,0) -> 35295.92 | F53: =IFERROR('Data Sheet'!D60,0) -> 43696.2 | G53: =IFERROR('Data Sheet'!E60,0) -> 51056.95 | H53: =IFERROR('Data Sheet'!F60,0) -> 43654.54 | I53: =IFERROR('Data Sheet'!G60,0) -> 42761.58 | J53: =IFERROR('Data Sheet'!H60,0) -> 47660.64 | K53: =IFERROR('Data Sheet'!I60,0) -> 55670.49 | ... M53: =IFERROR('Data Sheet'!K60,0) -> 69949.72
B54: Total Liabilities | D54: =SUM(D50:D53) -> 99851.82 | E54: =SUM(E50:E53) -> 113835.48 | F54: =SUM(F50:F53) -> 136369.31 | G54: =SUM(G50:G53) -> 161888.66 | H54: =SUM(H50:H53) -> 165716.13 | I54: =SUM(I50:I53) -> 164968.33 | J54: =SUM(J50:J53) -> 172388.49 | K54: =SUM(K50:K53) -> 204283.13 | ... M54: =SUM(M50:M53) -> 276013.16
B56: Net Block | D56: =IFERROR('Data Sheet'!B62,0) -> 20584.71 | E56: =IFERROR('Data Sheet'!C62,0) -> 20989.01 | F56: =IFERROR('Data Sheet'!D62,0) -> 26181.9 | G56: =IFERROR('Data Sheet'!E62,0) -> 28982.74 | H56: =IFERROR('Data Sheet'!F62,0) -> 29689.27 | I56: =IFERROR('Data Sheet'!G62,0) -> 21379.68 | J56: =IFERROR('Data Sheet'!H62,0) -> 26018.49 | K56: =IFERROR('Data Sheet'!I62,0) -> 27139.98 | ... M56: =IFERROR('Data Sheet'!K62,0) -> 34636.36
B57: Capital Work in Progress | D57: =IFERROR('Data Sheet'!B63,0) -> 2371.35 | E57: =IFERROR('Data Sheet'!C63,0) -> 4278.94 | F57: =IFERROR('Data Sheet'!D63,0) -> 4269.47 | G57: =IFERROR('Data Sheet'!E63,0) -> 4759.84 | H57: =IFERROR('Data Sheet'!F63,0) -> 6856.48 | I57: =IFERROR('Data Sheet'!G63,0) -> 7872.61 | J57: =IFERROR('Data Sheet'!H63,0) -> 6702.81 | K57: =IFERROR('Data Sheet'!I63,0) -> 3968.58 | ... M57: =IFERROR('Data Sheet'!K63,0) -> 8297.64
B58: Investments | D58: =IFERROR('Data Sheet'!B64,0) -> 11602.58 | E58: =IFERROR('Data Sheet'!C64,0) -> 14662.44 | F58: =IFERROR('Data Sheet'!D64,0) -> 16017.61 | G58: =IFERROR('Data Sheet'!E64,0) -> 18268.1 | H58: =IFERROR('Data Sheet'!F64,0) -> 19210.34 | I58: =IFERROR('Data Sheet'!G64,0) -> 28777.66 | J58: =IFERROR('Data Sheet'!H64,0) -> 30060.43 | K58: =IFERROR('Data Sheet'!I64,0) -> 35272.42 | ... M58: =IFERROR('Data Sheet'!K64,0) -> 41308.57
B59: Other Assets | D59: =IFERROR('Data Sheet'!B65-SUM('Data Sheet'!B67:B69),0) -> 45831.91 | E59: =IFERROR('Data Sheet'!C65-SUM('Data Sheet'!C67:C69),0) -> 53165.79 | F59: =IFERROR('Data Sheet'!D65-SUM('Data Sheet'!D67:D69),0) -> 65527.34 | G59: =IFERROR('Data Sheet'!E65-SUM('Data Sheet'!E67:E69),0) -> 80265.02 | H59: =IFERROR('Data Sheet'!F65-SUM('Data Sheet'!F67:F69),0) -> 84009 | I59: =IFERROR('Data Sheet'!G65-SUM('Data Sheet'!G67:G69),0) -> 78463.22 | J59: =IFERROR('Data Sheet'!H65-SUM('Data Sheet'!H67:H69),0) -> 80519.38 | K59: =IFERROR('Data Sheet'!I65-SUM('Data Sheet'!I67:I69),0) -> 102745.73 | ... M59: =IFERROR('Data Sheet'!K65-SUM('Data Sheet'!K67:K69),0) -> 142545.12
B60: Total Non-current Assets | D60: =IFERROR(SUM(D56:D59),0) -> 80390.55 | E60: =IFERROR(SUM(E56:E59),0) -> 93096.18 | F60: =IFERROR(SUM(F56:F59),0) -> 111996.32 | G60: =IFERROR(SUM(G56:G59),0) -> 132275.7 | H60: =IFERROR(SUM(H56:H59),0) -> 139765.09 | I60: =IFERROR(SUM(I56:I59),0) -> 136493.17 | J60: =IFERROR(SUM(J56:J59),0) -> 143301.11 | K60: =IFERROR(SUM(K56:K59),0) -> 169126.71 | ... M60: =IFERROR(SUM(M56:M59),0) -> 226787.69
B62: Receivables | D62: ='Data Sheet'!B67 -> 5817.6 | E62: ='Data Sheet'!C67 -> 7199.26 | F62: ='Data Sheet'!D67 -> 8489.82 | G62: ='Data Sheet'!E67 -> 8677.89 | H62: ='Data Sheet'!F67 -> 6928.28 | I62: ='Data Sheet'!G67 -> 6007.76 | J62: ='Data Sheet'!H67 -> 6373.95 | K62: ='Data Sheet'!I67 -> 7028.02 | ... M62: ='Data Sheet'!K67 -> 8279.7
B63: Inventory | D63: ='Data Sheet'!B68 -> 9116.12 | E63: ='Data Sheet'!C68 -> 8886.01 | F63: ='Data Sheet'!D68 -> 9335.57 | G63: ='Data Sheet'!E68 -> 12200.16 | H63: ='Data Sheet'!F68 -> 11111.86 | I63: ='Data Sheet'!G68 -> 9615.41 | J63: ='Data Sheet'!H68 -> 11595.82 | K63: ='Data Sheet'!I68 -> 16854.97 | ... M63: ='Data Sheet'!K68 -> 20330.93
B64: Cash & Bank | D64: ='Data Sheet'!B69 -> 4527.55 | E64: ='Data Sheet'!C69 -> 4654.03 | F64: ='Data Sheet'!D69 -> 6547.6 | G64: ='Data Sheet'!E69 -> 8734.91 | H64: ='Data Sheet'!F69 -> 7910.9 | I64: ='Data Sheet'!G69 -> 12851.99 | J64: ='Data Sheet'!H69 -> 11117.61 | K64: ='Data Sheet'!I69 -> 11273.43 | ... M64: ='Data Sheet'!K69 -> 20614.84
B65: Total Current Assets | D65: =IFERROR(SUM(D62:D64),0) -> 19461.27 | E65: =IFERROR(SUM(E62:E64),0) -> 20739.3 | F65: =IFERROR(SUM(F62:F64),0) -> 24372.99 | G65: =IFERROR(SUM(G62:G64),0) -> 29612.96 | H65: =IFERROR(SUM(H62:H64),0) -> 25951.04 | I65: =IFERROR(SUM(I62:I64),0) -> 28475.16 | J65: =IFERROR(SUM(J62:J64),0) -> 29087.38 | K65: =IFERROR(SUM(K62:K64),0) -> 35156.42 | ... M65: =IFERROR(SUM(M62:M64),0) -> 49225.47
B67: Total Assets | D67: =IFERROR((D60+D65),0) -> 99851.82 | E67: =IFERROR((E60+E65),0) -> 113835.48 | F67: =IFERROR((F60+F65),0) -> 136369.31 | G67: =IFERROR((G60+G65),0) -> 161888.66 | H67: =IFERROR((H60+H65),0) -> 165716.13 | I67: =IFERROR((I60+I65),0) -> 164968.33 | J67: =IFERROR((J60+J65),0) -> 172388.49 | K67: =IFERROR((K60+K65),0) -> 204283.13 | ... M67: =IFERROR((M60+M65),0) -> 276013.16
B69: Check | D69: =D67=D54 -> TRUE | E69: =E67=E54 -> TRUE | F69: =F67=F54 -> TRUE | G69: =G67=G54 -> TRUE | H69: =H67=H54 -> TRUE | I69: =I67=I54 -> TRUE | J69: =J67=J54 -> TRUE | K69: =K67=K54 -> TRUE | ... M69: =M67=M54 -> TRUE
B72: Cashflow Statement
B73: In Crores
B74: Profit from operations | D74: =IFERROR('Raw CF Data'!E5,0) -> 7595 | E74: =IFERROR('Raw CF Data'!F5,0) -> 7911 | F74: =IFERROR('Raw CF Data'!G5,0) -> 10159 | G74: =IFERROR('Raw CF Data'!H5,0) -> 11112 | H74: =IFERROR('Raw CF Data'!I5,0) -> 7774 | I74: =IFERROR('Raw CF Data'!J5,0) -> 7588 | J74: =IFERROR('Raw CF Data'!K5,0) -> 10515 | K74: =IFERROR('Raw CF Data'!L5,0) -> 15642 | ... M74: =IFERROR('Raw CF Data'!N5,0) -> 22050
B75: Receivables | D75: =IFERROR('Raw CF Data'!E6,0) -> 177 | E75: =IFERROR('Raw CF Data'!F6,0) -> -8609 | F75: =IFERROR('Raw CF Data'!G6,0) -> -11918 | G75: =IFERROR('Raw CF Data'!H6,0) -> -13712 | H75: =IFERROR('Raw CF Data'!I6,0) -> -1516 | I75: =IFERROR('Raw CF Data'!J6,0) -> 4896 | J75: =IFERROR('Raw CF Data'!K6,0) -> -2506 | K75: =IFERROR('Raw CF Data'!L6,0) -> -21702 | ... M75: =IFERROR('Raw CF Data'!N6,0) -> -20952
B76: Inventory | D76: =IFERROR('Raw CF Data'!E7,0) -> -1113 | E76: =IFERROR('Raw CF Data'!F7,0) -> 241 | F76: =IFERROR('Raw CF Data'!G7,0) -> -256 | G76: =IFERROR('Raw CF Data'!H7,0) -> -2276 | H76: =IFERROR('Raw CF Data'!I7,0) -> 1316 | I76: =IFERROR('Raw CF Data'!J7,0) -> 226 | J76: =IFERROR('Raw CF Data'!K7,0) -> -2173 | K76: =IFERROR('Raw CF Data'!L7,0) -> -5252 | ... M76: =IFERROR('Raw CF Data'!N7,0) -> -1646
B77: Payables | D77: =IFERROR('Raw CF Data'!E8,0) -> 1939 | E77: =IFERROR('Raw CF Data'!F8,0) -> 2645 | F77: =IFERROR('Raw CF Data'!G8,0) -> 5361 | G77: =IFERROR('Raw CF Data'!H8,0) -> 3466 | H77: =IFERROR('Raw CF Data'!I8,0) -> -6775 | I77: =IFERROR('Raw CF Data'!J8,0) -> 7049 | J77: =IFERROR('Raw CF Data'!K8,0) -> 4972 | K77: =IFERROR('Raw CF Data'!L8,0) -> 7013 | ... M77: =IFERROR('Raw CF Data'!N8,0) -> 8485
B78: Loans Advances | D78: =IFERROR('Raw CF Data'!E9,0) -> 0 | E78: =IFERROR('Raw CF Data'!F9,0) -> 0 | F78: =IFERROR('Raw CF Data'!G9,0) -> 0 | G78: =IFERROR('Raw CF Data'!H9,0) -> 0 | H78: =IFERROR('Raw CF Data'!I9,0) -> 0 | I78: =IFERROR('Raw CF Data'!J9,0) -> 0 | J78: =IFERROR('Raw CF Data'!K9,0) -> 0 | K78: =IFERROR('Raw CF Data'!L9,0) -> 0 | ... M78: =IFERROR('Raw CF Data'!N9,0) -> 0
B79: Other WC items | D79: =IFERROR('Raw CF Data'!E10,0) -> -4241 | E79: =IFERROR('Raw CF Data'!F10,0) -> 0 | F79: =IFERROR('Raw CF Data'!G10,0) -> 0 | G79: =IFERROR('Raw CF Data'!H10,0) -> 0 | H79: =IFERROR('Raw CF Data'!I10,0) -> 0 | I79: =IFERROR('Raw CF Data'!J10,0) -> 0 | J79: =IFERROR('Raw CF Data'!K10,0) -> 0 | K79: =IFERROR('Raw CF Data'!L10,0) -> 0 | ... M79: =IFERROR('Raw CF Data'!N10,0) -> 0
B80: Working capital changes | D80: =IFERROR('Raw CF Data'!E11,0) -> -3238 | E80: =IFERROR('Raw CF Data'!F11,0) -> -5724 | F80: =IFERROR('Raw CF Data'!G11,0) -> -6813 | G80: =IFERROR('Raw CF Data'!H11,0) -> -12522 | H80: =IFERROR('Raw CF Data'!I11,0) -> -6974 | I80: =IFERROR('Raw CF Data'!J11,0) -> 12171 | J80: =IFERROR('Raw CF Data'!K11,0) -> 293 | K80: =IFERROR('Raw CF Data'!L11,0) -> -19941 | ... M80: =IFERROR('Raw CF Data'!N11,0) -> -14113
B81: Direct taxes | D81: =IFERROR('Raw CF Data'!E12,0) -> -1973 | E81: =IFERROR('Raw CF Data'!F12,0) -> -2005 | F81: =IFERROR('Raw CF Data'!G12,0) -> -2664 | G81: =IFERROR('Raw CF Data'!H12,0) -> -2937 | H81: =IFERROR('Raw CF Data'!I12,0) -> -2257 | I81: =IFERROR('Raw CF Data'!J12,0) -> -1850 | J81: =IFERROR('Raw CF Data'!K12,0) -> -1560 | K81: =IFERROR('Raw CF Data'!L12,0) -> -2775 | ... M81: =IFERROR('Raw CF Data'!N12,0) -> -4761
B82: Cash from Operating Activity | D82: =IFERROR(SUM(D74:D81),0) -> -854 | E82: =IFERROR(SUM(E74:E81),0) -> -5541 | F82: =IFERROR(SUM(F74:F81),0) -> -6131 | G82: =IFERROR(SUM(G74:G81),0) -> -16869 | H82: =IFERROR(SUM(H74:H81),0) -> -8432 | I82: =IFERROR(SUM(I74:I81),0) -> 30080 | J82: =IFERROR(SUM(J74:J81),0) -> 9541 | K82: =IFERROR(SUM(K74:K81),0) -> -27015 | ... M82: =IFERROR(SUM(M74:M81),0) -> -10937
B84: Fixed assets purchased | D84: =IFERROR('Raw CF Data'!E15,0) -> -4172 | E84: =IFERROR('Raw CF Data'!F15,0) -> -5026 | F84: =IFERROR('Raw CF Data'!G15,0) -> -5906 | G84: =IFERROR('Raw CF Data'!H15,0) -> -7340 | H84: =IFERROR('Raw CF Data'!I15,0) -> -6896 | I84: =IFERROR('Raw CF Data'!J15,0) -> -5989 | J84: =IFERROR('Raw CF Data'!K15,0) -> -6040 | K84: =IFERROR('Raw CF Data'!L15,0) -> -6305 | ... M84: =IFERROR('Raw CF Data'!N15,0) -> -10392
B85: Fixed assets sold | D85: =IFERROR('Raw CF Data'!E16,0) -> 59 | E85: =IFERROR('Raw CF Data'!F16,0) -> 63 | F85: =IFERROR('Raw CF Data'!G16,0) -> 115 | G85: =IFERROR('Raw CF Data'!H16,0) -> 142 | H85: =IFERROR('Raw CF Data'!I16,0) -> 102 | I85: =IFERROR('Raw CF Data'!J16,0) -> 1364 | J85: =IFERROR('Raw CF Data'!K16,0) -> 120 | K85: =IFERROR('Raw CF Data'!L16,0) -> 138 | ... M85: =IFERROR('Raw CF Data'!N16,0) -> 583
B86: Investments purchased | D86: =IFERROR('Raw CF Data'!E17,0) -> -87898 | E86: =IFERROR('Raw CF Data'!F17,0) -> -132173 | F86: =IFERROR('Raw CF Data'!G17,0) -> -155159 | G86: =IFERROR('Raw CF Data'!H17,0) -> -196474 | H86: =IFERROR('Raw CF Data'!I17,0) -> -198568 | I86: =IFERROR('Raw CF Data'!J17,0) -> -120055 | J86: =IFERROR('Raw CF Data'!K17,0) -> -65421 | K86: =IFERROR('Raw CF Data'!L17,0) -> -50165 | ... M86: =IFERROR('Raw CF Data'!N17,0) -> -90595
B87: Investments sold | D87: =IFERROR('Raw CF Data'!E18,0) -> 86436 | E87: =IFERROR('Raw CF Data'!F18,0) -> 130940 | F87: =IFERROR('Raw CF Data'!G18,0) -> 154631 | G87: =IFERROR('Raw CF Data'!H18,0) -> 195898 | H87: =IFERROR('Raw CF Data'!I18,0) -> 198132 | I87: =IFERROR('Raw CF Data'!J18,0) -> 111749 | J87: =IFERROR('Raw CF Data'!K18,0) -> 65127 | K87: =IFERROR('Raw CF Data'!L18,0) -> 46269 | ... M87: =IFERROR('Raw CF Data'!N18,0) -> 85257
B88: Interest received | D88: =IFERROR('Raw CF Data'!E19,0) -> 311 | E88: =IFERROR('Raw CF Data'!F19,0) -> 346 | F88: =IFERROR('Raw CF Data'!G19,0) -> 254 | G88: =IFERROR('Raw CF Data'!H19,0) -> 314 | H88: =IFERROR('Raw CF Data'!I19,0) -> 372 | I88: =IFERROR('Raw CF Data'!J19,0) -> 431 | J88: =IFERROR('Raw CF Data'!K19,0) -> 420 | K88: =IFERROR('Raw CF Data'!L19,0) -> 464 | ... M88: =IFERROR('Raw CF Data'!N19,0) -> 884
B89: Dividends received | D89: =IFERROR('Raw CF Data'!E20,0) -> 208 | E89: =IFERROR('Raw CF Data'!F20,0) -> 409 | F89: =IFERROR('Raw CF Data'!G20,0) -> 316 | G89: =IFERROR('Raw CF Data'!H20,0) -> 466 | H89: =IFERROR('Raw CF Data'!I20,0) -> 722 | I89: =IFERROR('Raw CF Data'!J20,0) -> 577 | J89: =IFERROR('Raw CF Data'!K20,0) -> 1247 | K89: =IFERROR('Raw CF Data'!L20,0) -> 1397 | ... M89: =IFERROR('Raw CF Data'!N20,0) -> 1374
B90: Investment in group cos | D90: =IFERROR('Raw CF Data'!E21,0) -> -147 | E90: =IFERROR('Raw CF Data'!F21,0) -> -647 | F90: =IFERROR('Raw CF Data'!G21,0) -> -704 | G90: =IFERROR('Raw CF Data'!H21,0) -> -319 | H90: =IFERROR('Raw CF Data'!I21,0) -> -418 | I90: =IFERROR('Raw CF Data'!J21,0) -> -359 | J90: =IFERROR('Raw CF Data'!K21,0) -> -222 | K90: =IFERROR('Raw CF Data'!L21,0) -> -62 | ... M90: =IFERROR('Raw CF Data'!N21,0) -> -29
B91: Issue of shares on acq | D91: =IFERROR('Raw CF Data'!E22,0) -> 0 | E91: =IFERROR('Raw CF Data'!F22,0) -> 0 | F91: =IFERROR('Raw CF Data'!G22,0) -> 0 | G91: =IFERROR('Raw CF Data'!H22,0) -> 0 | H91: =IFERROR('Raw CF Data'!I22,0) -> 0 | I91: =IFERROR('Raw CF Data'!J22,0) -> 0 | J91: =IFERROR('Raw CF Data'!K22,0) -> 0 | K91: =IFERROR('Raw CF Data'!L22,0) -> 0 | ... M91: =IFERROR('Raw CF Data'!N22,0) -> 0
B92: Redemp n Canc of Shares | D92: =IFERROR('Raw CF Data'!E23,0) -> 0 | E92: =IFERROR('Raw CF Data'!F23,0) -> 88 | F92: =IFERROR('Raw CF Data'!G23,0) -> 1677 | G92: =IFERROR('Raw CF Data'!H23,0) -> 717 | H92: =IFERROR('Raw CF Data'!I23,0) -> 175 | I92: =IFERROR('Raw CF Data'!J23,0) -> 316 | J92: =IFERROR('Raw CF Data'!K23,0) -> 617 | K92: =IFERROR('Raw CF Data'!L23,0) -> 1863 | ... M92: =IFERROR('Raw CF Data'!N23,0) -> 620
B93: Acquisition of companies | D93: =IFERROR('Raw CF Data'!E24,0) -> -208 | E93: =IFERROR('Raw CF Data'!F24,0) -> -83 | F93: =IFERROR('Raw CF Data'!G24,0) -> -401 | G93: =IFERROR('Raw CF Data'!H24,0) -> 0 | H93: =IFERROR('Raw CF Data'!I24,0) -> -59 | I93: =IFERROR('Raw CF Data'!J24,0) -> 0 | J93: =IFERROR('Raw CF Data'!K24,0) -> -42 | K93: =IFERROR('Raw CF Data'!L24,0) -> -587 | ... M93: =IFERROR('Raw CF Data'!N24,0) -> 0
B94: Inter corporate deposits | D94: =IFERROR('Raw CF Data'!E25,0) -> 0 | E94: =IFERROR('Raw CF Data'!F25,0) -> 0 | F94: =IFERROR('Raw CF Data'!G25,0) -> 0 | G94: =IFERROR('Raw CF Data'!H25,0) -> 0 | H94: =IFERROR('Raw CF Data'!I25,0) -> 6 | I94: =IFERROR('Raw CF Data'!J25,0) -> -262 | J94: =IFERROR('Raw CF Data'!K25,0) -> -552 | K94: =IFERROR('Raw CF Data'!L25,0) -> -93 | ... M94: =IFERROR('Raw CF Data'!N25,0) -> -244
B95: Other investing items | D95: =IFERROR('Raw CF Data'!E26,0) -> -94 | E95: =IFERROR('Raw CF Data'!F26,0) -> 209 | F95: =IFERROR('Raw CF Data'!G26,0) -> -290 | G95: =IFERROR('Raw CF Data'!H26,0) -> -577 | H95: =IFERROR('Raw CF Data'!I26,0) -> -437 | I95: =IFERROR('Raw CF Data'!J26,0) -> -7457 | J95: =IFERROR('Raw CF Data'!K26,0) -> 1494 | K95: =IFERROR('Raw CF Data'!L26,0) -> -1786 | ... M95: =IFERROR('Raw CF Data'!N26,0) -> -6075
B96: Cash from Investing Activity | D96: =IFERROR(SUM(D84:D95),0) -> -5505 | E96: =IFERROR(SUM(E84:E95),0) -> -5874 | F96: =IFERROR(SUM(F84:F95),0) -> -5467 | G96: =IFERROR(SUM(G84:G95),0) -> -7173 | H96: =IFERROR(SUM(H84:H95),0) -> -6869 | I96: =IFERROR(SUM(I84:I95),0) -> -19685 | J96: =IFERROR(SUM(J84:J95),0) -> -3252 | K96: =IFERROR(SUM(K84:K95),0) -> -8867 | ... M96: =IFERROR(SUM(M84:M95),0) -> -18617
B98: Proceeds from shares | D98: =IFERROR('Raw CF Data'!E29,0) -> 18 | E98: =IFERROR('Raw CF Data'!F29,0) -> 12 | F98: =IFERROR('Raw CF Data'!G29,0) -> 4 | G98: =IFERROR('Raw CF Data'!H29,0) -> 1 | H98: =IFERROR('Raw CF Data'!I29,0) -> 1243 | I98: =IFERROR('Raw CF Data'!J29,0) -> 1 | J98: =IFERROR('Raw CF Data'!K29,0) -> 1 | K98: =IFERROR('Raw CF Data'!L29,0) -> 1 | ... M98: =IFERROR('Raw CF Data'!N29,0) -> 1
B99: Proceeds from borrowings | D99: =IFERROR('Raw CF Data'!E30,0) -> 0 | E99: =IFERROR('Raw CF Data'!F30,0) -> 0 | F99: =IFERROR('Raw CF Data'!G30,0) -> 0 | G99: =IFERROR('Raw CF Data'!H30,0) -> 71389 | H99: =IFERROR('Raw CF Data'!I30,0) -> 52618 | I99: =IFERROR('Raw CF Data'!J30,0) -> 38100 | J99: =IFERROR('Raw CF Data'!K30,0) -> 53880 | K99: =IFERROR('Raw CF Data'!L30,0) -> 55622 | ... M99: =IFERROR('Raw CF Data'!N30,0) -> 82590
B100: Repayment of borrowings | D100: =IFERROR('Raw CF Data'!E31,0) -> 0 | E100: =IFERROR('Raw CF Data'!F31,0) -> 0 | F100: =IFERROR('Raw CF Data'!G31,0) -> 0 | G100: =IFERROR('Raw CF Data'!H31,0) -> -56352 | H100: =IFERROR('Raw CF Data'!I31,0) -> -44044 | I100: =IFERROR('Raw CF Data'!J31,0) -> -37505 | J100: =IFERROR('Raw CF Data'!K31,0) -> -57223 | K100: =IFERROR('Raw CF Data'!L31,0) -> -37056 | ... M100: =IFERROR('Raw CF Data'!N31,0) -> -64689
B101: Interest paid fin | D101: =IFERROR('Raw CF Data'!E32,0) -> -443 | E101: =IFERROR('Raw CF Data'!F32,0) -> -471 | F101: =IFERROR('Raw CF Data'!G32,0) -> -521 | G101: =IFERROR('Raw CF Data'!H32,0) -> -723 | H101: =IFERROR('Raw CF Data'!I32,0) -> -624 | I101: =IFERROR('Raw CF Data'!J32,0) -> -809 | J101: =IFERROR('Raw CF Data'!K32,0) -> -680 | K101: =IFERROR('Raw CF Data'!L32,0) -> -734 | ... M101: =IFERROR('Raw CF Data'!N32,0) -> -436
B102: Dividends paid | D102: =IFERROR('Raw CF Data'!E33,0) -> -932 | E102: =IFERROR('Raw CF Data'!F33,0) -> -936 | F102: =IFERROR('Raw CF Data'!G33,0) -> -963 | G102: =IFERROR('Raw CF Data'!H33,0) -> -1134 | H102: =IFERROR('Raw CF Data'!I33,0) -> -1398 | I102: =IFERROR('Raw CF Data'!J33,0) -> -271 | J102: =IFERROR('Raw CF Data'!K33,0) -> -1037 | K102: =IFERROR('Raw CF Data'!L33,0) -> -1522 | ... M102: =IFERROR('Raw CF Data'!N33,0) -> -2806
B103: Financial liabilities | D103: =IFERROR('Raw CF Data'!E34,0) -> 0 | E103: =IFERROR('Raw CF Data'!F34,0) -> 0 | F103: =IFERROR('Raw CF Data'!G34,0) -> 0 | G103: =IFERROR('Raw CF Data'!H34,0) -> 0 | H103: =IFERROR('Raw CF Data'!I34,0) -> -558 | I103: =IFERROR('Raw CF Data'!J34,0) -> -553 | J103: =IFERROR('Raw CF Data'!K34,0) -> -583 | K103: =IFERROR('Raw CF Data'!L34,0) -> -751 | ... M103: =IFERROR('Raw CF Data'!N34,0) -> -887
B104: Other financing items | D104: =IFERROR('Raw CF Data'!E35,0) -> 4324 | E104: =IFERROR('Raw CF Data'!F35,0) -> 7503 | F104: =IFERROR('Raw CF Data'!G35,0) -> 7794 | G104: =IFERROR('Raw CF Data'!H35,0) -> 12 | H104: =IFERROR('Raw CF Data'!I35,0) -> -304 | I104: =IFERROR('Raw CF Data'!J35,0) -> 1444 | J104: =IFERROR('Raw CF Data'!K35,0) -> -240 | K104: =IFERROR('Raw CF Data'!L35,0) -> 386 | ... M104: =IFERROR('Raw CF Data'!N35,0) -> 2062
B105: Cash from Financing Activity | D105: =IFERROR(SUM(D98:D104),0) -> 2967 | E105: =IFERROR(SUM(E98:E104),0) -> 6108 | F105: =IFERROR(SUM(F98:F104),0) -> 6314 | G105: =IFERROR(SUM(G98:G104),0) -> 13193 | H105: =IFERROR(SUM(H98:H104),0) -> 6933 | I105: =IFERROR(SUM(I98:I104),0) -> 407 | J105: =IFERROR(SUM(J98:J104),0) -> -5882 | K105: =IFERROR(SUM(K98:K104),0) -> 15946 | ... M105: =IFERROR(SUM(M98:M104),0) -> 15835
B107: Net Cash Flow | D107: =IFERROR((D105+D96+D82),0) -> -3392 | E107: =IFERROR((E105+E96+E82),0) -> -5307 | F107: =IFERROR((F105+F96+F82),0) -> -5284 | G107: =IFERROR((G105+G96+G82),0) -> -10849 | H107: =IFERROR((H105+H96+H82),0) -> -8368 | I107: =IFERROR((I105+I96+I82),0) -> 10802 | J107: =IFERROR((J105+J96+J82),0) -> 407 | K107: =IFERROR((K105+K96+K82),0) -> -19936 | ... M107: =IFERROR((M105+M96+M82),0) -> -13719

Sheet Historicals>

Sheet DATA>

Sheet Data Sheet
A1: COMPANY NAME | B1: MAHINDRA & MAHINDRA LTD | E1: =IF(B2<>B3, "A NEW VERSION OF THE WORKSHEET IS AVAILABLE", "")
A2: LATEST VERSION | B2: 2.1 | E2: PLEASE DO NOT MAKE ANY CHANGES TO THIS SHEET
A3: CURRENT VERSION | B3: 2.1
A5: META
A6: Number of shares | B6: =IF(B9>0, B9/B8, 0) -> 124.35289
A7: Face Value | B7: 5
A8: Current Price | B8: 3650.15
A9: Market Capitalization | B9: 453906.71
A15: PROFIT & LOSS | B15: =B26+B34 -> 13516.85 | K15: =K17-K18-K20-K21-K22-K23-K19 -> 36511.54
A16: Report Date | B16: 42460 | C16: 42825 | D16: 43190 | E16: 43555 | F16: 43921 | G16: 44286 | H16: 44651 | I16: 45016 | J16: 45382 | K16: 45747
A17: Sales | B17: 75841.42 | C17: 83773.05 | D17: 92093.95 | E17: 104720.68 | F17: 75381.93 | G17: 74277.78 | H17: 90170.57 | I17: 121268.55 | J17: 139078.27 | K17: 159210.82
A18: Raw Material Cost | B18: 45584.35 | C18: 50655.2 | D18: 53457.29 | E18: 61881.19 | F18: 37595.3 | G18: 38271.2 | H18: 52664.85 | I18: 76019.87 | J18: 85070.07 | K18: 95754.9
A19: Change in Inventory | B19: 458.51 | C19: 13.83 | D19: -83.33 | E19: 1730.48 | F19: -826.62 | G19: -135.59 | H19: 861.66 | I19: 2032.31 | J19: 1455.32 | K19: 12.18
A20: Power and Fuel | B20: 639.97 | C20: 657.06 | D20: 733.9 | E20: 817.11 | F20: 530.92 | G20: 429.56 | H20: 541.27 | I20: 830.48 | J20: 752.73 | K20: 832.35
A21: Other Mfr. Exp | B21: 2618.7 | C21: 3255.3 | D21: 3590.26 | E21: 4253 | F21: 3277.79 | G21: 2523.4 | H21: 3124.27 | I21: 3838.42 | J21: 3791.75 | K21: 4162.28
A22: Employee Cost | B22: 7689.4 | C22: 8910.63 | D22: 10004.62 | E22: 11242.08 | F22: 8214.82 | G22: 7813.26 | H22: 8386.74 | I22: 9677.95 | J22: 10624.33 | K22: 11126.17
A23: Selling and admin | B23: 5758.86 | C23: 6253.64 | D23: 7591.15 | E23: 9658.98 | F23: 6316.52 | G23: 4628.75 | H23: 5977.67 | I23: 7681.87 | J23: 9832.2 | K23: 10811.4
A24: Other Expenses | B24: 3926.21 | C24: 3320.22 | D24: 3407.3 | E24: 3392.29 | F24: 8462.21 | G24: 8989 | H24: 5654.58 | I24: 4966.98 | J24: 5570.58 | K24: 6017.71
A25: Other Income | B25: 1398.83 | C25: 2076.61 | D25: 4366.41 | E25: 2676.45 | F25: 884.69 | G25: 1151.51 | H25: 3204.47 | I25: 3961.45 | J25: 3297.85 | K25: 3718.47
A26: Depreciation | B26: 2441.65 | C26: 2812.72 | D26: 3279.9 | E26: 3990.77 | F26: 3366.68 | G26: 3378.11 | H26: 3507.5 | I26: 4356.81 | J26: 4723.78 | K26: 6073.65
A27: Interest | B27: 3367.59 | C27: 3648.46 | D27: 3987.09 | E27: 5021.35 | F27: 6021.15 | G27: 6102.22 | H27: 5018.05 | I27: 5829.7 | J27: 7488.21 | K27: 9083.39
... A31: Dividend Amount | B31: 648.96 | C31: 807.43 | D31: 814.7 | E31: 924.73 | F31: 260.51 | G31: 971.51 | H31: 1284.5 | I31: 1809.66 | J31: 2352.14 | K31: 2824.24
A32: Effective Tax Rate | B32: =B29/B28 -> 0.37332842 | C32: =C29/C28 -> 0.36214738 | D32: =D29/D28 -> 0.22930855 | E32: =E29/E28 -> 0.32172714 | F32: =F29/F28 -> 1.1940034 | G32: =G29/G28 -> 0.52112279 | H32: =H29/H28 -> 0.22525228 | I32: =I29/I28 -> 0.1910175 | ... K32: =K29/K28 -> 0.26239778
A34: EBITDA | B34: =+B30+B29+B27+B26 -> 11075.2 | C34: =+C30+C29+C27+C26 -> 12458.95 | D34: =+D30+D29+D27+D26 -> 17145.11 | E34: =+E30+E29+E27+E26 -> 17181.57 | F34: =+F30+F29+F27+F26 -> 11490.48 | G34: =+G30+G29+G27+G26 -> 12938.63 | H34: =+H30+H29+H27+H26 -> 17211.63 | I34: =+I30+I29+I27+I26 -> 23153.76 | ... K34: =+K30+K29+K27+K26 -> 33092.59
A40: Quarters
A41: Report Date | B41: 45107 | C41: 45199 | D41: 45291 | E41: 45382 | F41: 45473 | G41: 45565 | H41: 45657 | I41: 45747 | J41: 45838 | K41: 45930
A42: Sales | B42: 33891.63 | C42: 34435.52 | D42: 35299.39 | E42: 35451.73 | F42: 37217.72 | G42: 37923.74 | H42: 41470.05 | I42: 42599.31 | J42: 45529.19 | K42: 46105.67
A43: Expenses | B43: 27642.4 | C43: 28705.94 | D43: 29075.41 | E43: 28847.82 | F43: 29974.6 | G43: 30790.34 | H43: 33239.32 | I43: 34688.37 | J43: 37301.39 | K43: 37176.58
A44: Other Income | B44: 1065 | C44: 811.95 | D44: 755.69 | E44: 750.44 | F44: 733.21 | G44: 1125.57 | H44: 718.59 | I44: 1141.1 | J44: 1395.06 | K44: 1144.76
A45: Depreciation | B45: 1127.5 | C45: 1138.64 | D45: 1122.59 | E45: 1335.05 | F45: 1247.77 | G45: 1301.99 | H45: 1495.17 | I45: 2028.72 | J45: 1547.56 | K45: 1668.89
A46: Interest | B46: 1718.84 | C46: 1835.19 | D46: 1944.88 | E46: 1989.3 | F46: 2107.69 | G46: 2217.02 | H46: 2362.16 | I46: 2396.52 | J46: 2431.19 | K46: 2347.03
A47: Profit before tax | B47: 4467.89 | C47: 3567.7 | D47: 3912.2 | E47: 4030 | F47: 4620.87 | G47: 4739.96 | H47: 5091.99 | I47: 4626.8 | J47: 5644.11 | K47: 6057.93
A48: Tax | B48: 784.02 | C48: 1083.73 | D48: 935.16 | E48: 905.06 | F48: 1075.09 | G48: 1378.9 | H48: 1467.51 | I48: 1084.95 | J48: 1267.53 | K48: 2094.18
A49: Net profit | B49: 3508.41 | C49: 2347.75 | D49: 2658.4 | E49: 2754.08 | F49: 3282.63 | G49: 3170.72 | H49: 3180.58 | I49: 3295.17 | J49: 4083.32 | K49: 3673.32
A50: Operating Profit | B50: 6249.23 | C50: 5729.58 | D50: 6223.98 | E50: 6603.91 | F50: 7243.12 | G50: 7133.4 | H50: 8230.73 | I50: 7910.94 | J50: 8227.8 | K50: 8929.09
A51: EBITDA | B51: =B49+B48+B46+B45 -> 7138.77 | C51: =C49+C48+C46+C45 -> 6405.31 | D51: =D49+D48+D46+D45 -> 6661.03 | E51: =E49+E48+E46+E45 -> 6983.49 | F51: =F49+F48+F46+F45 -> 7713.18 | G51: =G49+G48+G46+G45 -> 8068.63 | H51: =H49+H48+H46+H45 -> 8505.42 | I51: =I49+I48+I46+I45 -> 8805.36 | ... K51: =K49+K48+K46+K45 -> 9783.42
A55: BALANCE SHEET
A56: Report Date | B56: 42460 | C56: 42825 | D56: 43190 | E56: 43555 | F56: 43921 | G56: 44286 | H56: 44651 | I56: 45016 | J56: 45382 | K56: 45747
A57: Equity Share Capital | B57: 270.4 | C57: 310.55 | D57: 543.13 | E57: 543.96 | F57: 554.28 | G57: 555.15 | H57: 556.06 | I57: 556.82 | J57: 557.38 | K57: 558.15
A58: Reserves | B58: 26222.25 | C58: 29467.1 | D58: 36232.06 | E58: 39439.45 | F58: 39415.03 | G58: 41026.77 | H58: 46566.58 | I58: 55808.97 | J58: 65633.17 | K58: 76480.71
A59: Borrowings | B59: 41552.93 | C59: 48761.91 | D59: 55897.92 | E59: 70848.3 | F59: 82092.28 | G59: 80624.83 | H59: 77605.21 | I59: 92246.85 | J59: 108647.25 | K59: 129024.58
A60: Other Liabilities | B60: 31806.24 | C60: 35295.92 | D60: 43696.2 | E60: 51056.95 | F60: 43654.54 | G60: 42761.58 | H60: 47660.64 | I60: 55670.49 | J60: 59883.94 | K60: 69949.72
A61: Total | B61: 99851.82 | C61: 113835.48 | D61: 136369.31 | E61: 161888.66 | F61: 165716.13 | G61: 164968.33 | H61: 172388.49 | I61: 204283.13 | J61: 234721.74 | K61: 276013.16
A62: Net Block | B62: 20584.71 | C62: 20989.01 | D62: 26181.9 | E62: 28982.74 | F62: 29689.27 | G62: 21379.68 | H62: 26018.49 | I62: 27139.98 | J62: 28129.41 | K62: 34636.36
A63: Capital Work in Progress | B63: 2371.35 | C63: 4278.94 | D63: 4269.47 | E63: 4759.84 | F63: 6856.48 | G63: 7872.61 | H63: 6702.81 | I63: 3968.58 | J63: 8039.3 | K63: 8297.64
A64: Investments | B64: 11602.58 | C64: 14662.44 | D64: 16017.61 | E64: 18268.1 | F64: 19210.34 | G64: 28777.66 | H64: 30060.43 | I64: 35272.42 | J64: 35208.1 | K64: 41308.57
A65: Other Assets | B65: 65293.18 | C65: 73905.09 | D65: 89900.33 | E65: 109877.98 | F65: 109960.04 | G65: 106938.38 | H65: 109606.76 | I65: 137902.15 | J65: 163344.93 | K65: 191770.59
A66: Total | B66: 99851.82 | C66: 113835.48 | D66: 136369.31 | E66: 161888.66 | F66: 165716.13 | G66: 164968.33 | H66: 172388.49 | I66: 204283.13 | J66: 234721.74 | K66: 276013.16
A67: Receivables | B67: 5817.6 | C67: 7199.26 | D67: 8489.82 | E67: 8677.89 | F67: 6928.28 | G67: 6007.76 | H67: 6373.95 | I67: 7028.02 | J67: 7459.4 | K67: 8279.7
... A70: No. of Equity Shares | B70: 592633807 | C70: 621092384 | D70: 1243192544 | E70: 1243192544 | F70: 1243192544 | G70: 1110297953 | H70: 1112130815 | I70: 1198118224 | J70: 1114775772 | K70: 1116313361
A71: New Bonus Shares | D71: 621596272
A72: Face value | B72: 5 | C72: 5 | D72: 5 | E72: 5 | F72: 5 | G72: 5 | H72: 5 | I72: 5 | J72: 5 | K72: 5
H73: =H62-G62+H45 -> 6133.98 | I73: =I62-H62+I45 -> 3150.21 | J73: =J62-I62+J45 -> 2536.99 | K73: =K62-J62+K45 -> 8175.84
A80: CASH FLOW:
A81: Report Date | B81: 42460 | C81: 42825 | D81: 43190 | E81: 43555 | F81: 43921 | G81: 44286 | H81: 44651 | I81: 45016 | J81: 45382 | K81: 45747
A82: Cash from Operating Activity | B82: 2384.76 | C82: 183.09 | D82: 681.86 | E82: -4347.29 | F82: -1456.93 | G82: 17908.83 | H82: 9247.55 | I82: -7074.02 | J82: -5629.95 | K82: 3175.81
A83: Cash from Investing Activity | B83: -5505.97 | C83: -5875.29 | D83: -5467.22 | E83: -7173.97 | F83: -6869.79 | G83: -19685.5 | H83: -3251.95 | I83: -8866.27 | J83: -5614.77 | K83: -18616.13
A84: Cash from Financing Activity | B84: 2966.81 | C84: 6107.97 | D84: 6314.5 | E84: 13193.63 | F84: 6932.75 | G84: 406.23 | H84: -5882.6 | I84: 15946.11 | J84: 12281.41 | K84: 15834.11
A85: Net Cash Flow | B85: -154.4 | C85: 415.77 | D85: 1529.14 | E85: 1672.37 | F85: -1393.97 | G85: -1370.44 | H85: 113 | I85: 5.82 | J85: 1036.69 | K85: 393.79
A90: PRICE: | B90: 605.35 | C90: 643.45 | D90: 738.9 | E90: 673.9 | F90: 284.95 | G90: 795.25 | H90: 806.55 | I90: 1158.7 | J90: 1921.35 | K90: 2665.8
A92: DERIVED:
A93: Adjusted Equity Shares in Cr | B93: 124.22 | C93: 124.22 | D93: 124.32 | E93: 124.32 | F93: 124.32 | G93: 124.32 | H93: 124.32 | I93: 124.35 | J93: 124.35 | K93: 124.35

Sheet Raw CF Data
B2: RAW CF DATA
C3: 41699 | D3: 42064 | E3: 42430 | F3: 42795 | G3: 43160 | H3: 43525 | I3: 43891 | J3: 44256 | K3: 44621 | L3: 44986 | M3: 45352 | N3: 45717
B5: Profit from operations | C5: 8086 | D5: 6454 | E5: 7595 | F5: 7911 | G5: 10159 | H5: 11112 | I5: 7774 | J5: 7588 | K5: 10515 | L5: 15642 | M5: 17541 | N5: 22050
B6: Receivables | C6: -2258 | D6: -575 | E6: 177 | F6: -8609 | G6: -11918 | H6: -13712 | I6: -1516 | J6: 4896 | K6: -2506 | L6: -21702 | M6: -21777 | N6: -20952
B7: Inventory | C7: -78 | D7: -62 | E7: -1113 | F7: 241 | G7: -256 | H7: -2276 | I7: 1316 | J7: 226 | K7: -2173 | L7: -5252 | M7: -1753 | N7: -1646
B8: Payables | C8: 1094 | D8: 1169 | E8: 1939 | F8: 2645 | G8: 5361 | H8: 3466 | I8: -6775 | J8: 7049 | K8: 4972 | L8: 7013 | M8: 4354 | N8: 8485
B9: Loans Advances | C9: -5814 | D9: -4229 | E9: 0 | F9: 0 | G9: 0 | H9: 0 | I9: 0 | J9: 0 | K9: 0 | L9: 0 | M9: 0 | N9: 0
B10: Other WC items | C10: 0 | D10: 0 | E10: -4241 | F10: 0 | G10: 0 | H10: 0 | I10: 0 | J10: 0 | K10: 0 | L10: 0 | M10: 0 | N10: 0
B11: Working capital changes | C11: -7055 | D11: -3698 | E11: -3238 | F11: -5724 | G11: -6813 | H11: -12522 | I11: -6974 | J11: 12171 | K11: 293 | L11: -19941 | M11: -19175 | N11: -14113
B12: Direct taxes | C12: -1275 | D12: -1701 | E12: -1973 | F12: -2005 | G12: -2664 | H12: -2937 | I12: -2257 | J12: -1850 | K12: -1560 | L12: -2775 | M12: -3996 | N12: -4761
B13: Cash from Operating Activity | C13: -244 | D13: 1055 | E13: 2385 | F13: 183 | G13: 682 | H13: -4347 | I13: -1457 | J13: 17909 | K13: 9248 | L13: -7074 | M13: -5630 | N13: 3176
B15: Fixed assets purchased | C15: -3665 | D15: -4759 | E15: -4172 | F15: -5026 | G15: -5906 | H15: -7340 | I15: -6896 | J15: -5989 | K15: -6040 | L15: -6305 | M15: -9946 | N15: -10392
B16: Fixed assets sold | C16: 58 | D16: 43 | E16: 59 | F16: 63 | G16: 115 | H16: 142 | I16: 102 | J16: 1364 | K16: 120 | L16: 138 | M16: 273 | N16: 583
B17: Investments purchased | C17: -66102 | D17: -80047 | E17: -87898 | F17: -132173 | G17: -155159 | H17: -196474 | I17: -198568 | J17: -120055 | K17: -65421 | L17: -50165 | M17: -49927 | N17: -90595
... B38: Net Cash Flow | C38: 810 | D38: -1633 | E38: -154 | F38: 416 | G38: 1529 | H38: 1672 | I38: -1394 | J38: -1370 | K38: 113 | L38: 6 | M38: 1037 | N38: 394
